doeasyeda/__init__.py
doeasyeda/create_area_plot.py
doeasyeda/create_hist_plot.py
doeasyeda/create_line_plot.py
doeasyeda/create_scatter_plot.py
doeasyeda/doeasyeda.py
doeasyeda-2.2.5.dist-info/LICENSE.md
doeasyeda-2.2.5.dist-info/METADATA
doeasyeda-2.2.5.dist-info/WHEEL
doeasyeda-2.2.5.dist-info/RECORD
