Metadata-Version: 2.1
Name: doeasyeda
Version: 2.2.5
Summary: This package creates standard EDA plots for your data.
License: MIT
Author: Riya Eliza
Requires-Python: >=3.9.0,<4.0.0
Classifier: License :: OSI Approved :: MIT License
Classifier: Programming Language :: Python :: 3
Classifier: Programming Language :: Python :: 3.9
Classifier: Programming Language :: Python :: 3.10
Classifier: Programming Language :: Python :: 3.11
Classifier: Programming Language :: Python :: 3.12
Requires-Dist: altair (==5.1.2)
